Metadata-Version: 2.1
Name: run-batched
Version: 1.0.2
Summary: Permanant cache.
Home-page: https://github.com/kavigupta/run_batched
Author: Kavi Gupta
Author-email: run-batched@kavigupta.org
Project-URL: Documentation, https://run-batched.readthedocs.io/en/latest/#
Classifier: Programming Language :: Python :: 3.9
Classifier: Programming Language :: Python :: 3.10
Classifier: Programming Language :: Python :: 3.11
Classifier: Programming Language :: Python :: 3.12
Classifier: Operating System :: OS Independent
Requires-Python: >=3.9
License-File: LICENSE
Requires-Dist: torch
Requires-Dist: numpy
